scraper/__init__.py
scraper/extra.py
scraper/telegraphscrape.py
telegraph_scraper-1.0.6.dist-info/LICENSE
telegraph_scraper-1.0.6.dist-info/METADATA
telegraph_scraper-1.0.6.dist-info/WHEEL
telegraph_scraper-1.0.6.dist-info/entry_points.txt
telegraph_scraper-1.0.6.dist-info/top_level.txt
telegraph_scraper-1.0.6.dist-info/RECORD
