Metadata-Version: 2.1
Name: telegraph-scraper
Version: 1.0.6
Summary: A Python scraper for Telegraph pages
Home-page: https://github.com/solodk/telegraph-scraper
Author: Mykola Solodky
Author-email: solodk.m@gmail.com
Keywords: telegraph scrape image images download
Classifier: Development Status :: 3 - Alpha
Classifier: Operating System :: OS Independent
Classifier: Programming Language :: Python :: 3
Classifier: Programming Language :: Python :: 3.7
Classifier: Programming Language :: Python :: 3.8
Classifier: Programming Language :: Python :: 3.9
License-File: LICENSE
Requires-Dist: tqdm
Requires-Dist: requests
